slicetime.py
slicetime-0.1.dist-info/LICENSE
slicetime-0.1.dist-info/WHEEL
slicetime-0.1.dist-info/METADATA
slicetime-0.1.dist-info/RECORD
