Metadata-Version: 2.1
Name: slicetime
Version: 0.1
Summary: Create time and datetime objects using slice notation
Keywords: slice,time,datetime
Author-email: Jeremiah Paige <ucodery@gmail.com>
Classifier: License :: OSI Approved :: MIT License
Requires-Dist: flit ; extra == "dev"
Requires-Dist: nox ; extra == "dev"
Requires-Dist: pytest >=2.7.3 ; extra == "test"
Requires-Dist: pytest_cases >=3.6.0,<4 ; extra == "test"
Project-URL: Home, https://github.com/ucodery/slicetime
Provides-Extra: dev
Provides-Extra: test
